pillar/__init__.py
pillar/_version.py
pillar/application.py
pillar/config.py
pillar/dataclass.py
pillar/exception.py
pillar/logging.py
pillar/py.typed
pillar/util.py
pillar-0.3.0.dist-info/LICENCE
pillar-0.3.0.dist-info/METADATA
pillar-0.3.0.dist-info/NOTICE
pillar-0.3.0.dist-info/WHEEL
pillar-0.3.0.dist-info/top_level.txt
pillar-0.3.0.dist-info/RECORD
