Metadata-Version: 2.1
Name: pillar
Version: 0.3.0
Summary: Building Blocks for Python Applications
Author-email: Nicholas Hairs <info+pillar@nicholashairs.com>
License: MIT
Project-URL: HomePage, https://nhairs.github.io/pillar
Project-URL: GitHub, https://github.com/nhairs/pillar
Classifier: Development Status :: 3 - Alpha
Classifier: Programming Language :: Python :: 3 :: Only
Classifier: Programming Language :: Python :: 3.7
Classifier: Programming Language :: Python :: 3.8
Classifier: Programming Language :: Python :: 3.9
Classifier: Programming Language :: Python :: 3.10
Classifier: Programming Language :: Python :: 3.11
Classifier: Programming Language :: Python :: 3.12
Classifier: License :: OSI Approved :: MIT License
Classifier: Intended Audience :: Developers
Classifier: Typing :: Typed
Requires-Python: >=3.7
License-File: LICENCE
License-File: NOTICE
Requires-Dist: colorlog
Requires-Dist: dataclassy
Requires-Dist: deepmerge
Requires-Dist: pyaml
Provides-Extra: dev
Requires-Dist: types-PyYAML ; extra == 'dev'
Requires-Dist: orjson ; extra == 'dev'
Requires-Dist: validate-pyproject[all] ; extra == 'dev'
Requires-Dist: black ; extra == 'dev'
Requires-Dist: pylint ; extra == 'dev'
Requires-Dist: mypy ; extra == 'dev'
Requires-Dist: pytest ; extra == 'dev'
Requires-Dist: bpython ; extra == 'dev'
Provides-Extra: docs
Requires-Dist: black ; extra == 'docs'
Requires-Dist: mkdocs ; extra == 'docs'
Requires-Dist: mkdocs-material >=8.5 ; extra == 'docs'
Requires-Dist: mkdocs-awesome-pages-plugin ; extra == 'docs'
Requires-Dist: mdx-truly-sane-lists ; extra == 'docs'
Requires-Dist: mkdocstrings[python] ; extra == 'docs'
Requires-Dist: mkdocs-gen-files ; extra == 'docs'
Requires-Dist: mkdocs-literate-nav ; extra == 'docs'
Requires-Dist: mike ; extra == 'docs'
Provides-Extra: recommended
Requires-Dist: orjson ; extra == 'recommended'
